{"data":{"current":4,"total":1183,"size":15,"records":[{"date":"2018-07-06 13:31:30","id":"577923782857125734c2eef988432c5f","title":"分析redis内存获取数据内容一个小小的java码农","content":"分析redis内存获取数据内容一个小小的java码农"},{"date":"2018-07-09 16:47:41","id":"0e82b606418086be09635c9405fe070a","title":"摸透一个员工很简单：只需认清6个问题夜谈职场","content":"摸透一个员工很简单：只需认清6个问题夜谈职场"},{"date":"2018-07-09 16:47:27","id":"f0b3137da0b797d322f1da7f24802999","title":"stickUp 插件 当向下拖动页面时，可以让任何页面元素，固定在浏览器窗口的顶部代码庸医","content":"stickUp 插件 当向下拖动页面时，可以让任何页面元素，固定在浏览器窗口的顶部代码庸医"},{"date":"2019-05-05 07:13:00","id":"27e1e2f008d8c6133e06938d607b4b5b","title":"自媒体快速写文章和获取素材的几大途径砍柴网","content":"自媒体快速写文章和获取素材的几大途径砍柴网"},{"date":"2018-07-06 11:41:43","id":"9306cb93eff18eb77fc9dba643bba924","title":"淘宝官方h5移动适配解决方案——Flexible.js专注做前端","content":"淘宝官方h5移动适配解决方案——Flexible.js专注做前端"},{"date":"2018-07-05 21:42:56","id":"11c780ebf5b95fd5111cb9a9751de9ce","title":"IT外包网络维护专家告诉你，黑客是如何攻破一个网站？夏掰创业","content":"IT外包网络维护专家告诉你，黑客是如何攻破一个网站？夏掰创业"},{"date":"2018-07-05 21:45:24","id":"76cea6695f63d02c550af2842fb57a53","title":"自建一个无限网盘 对接GoogleDrive实现高速访问和下载快乐小站长","content":"自建一个无限网盘 对接GoogleDrive实现高速访问和下载快乐小站长"},{"date":"2018-07-06 11:40:20","id":"31c02efbc68d816cf4839e9933baa1d2","title":"ApiDoc的使用（搭建自己的模板）PHP农仔","content":"ApiDoc的使用（搭建自己的模板）PHP农仔"},{"date":"2018-07-09 16:26:05","id":"cdc7f5984f762e18975067d19a85018e","title":"顶尖程序员：10分钟搭建hadoop环境，让同事膛目结舌！要开撕？大数据程序员之家","content":"顶尖程序员：10分钟搭建hadoop环境，让同事膛目结舌！要开撕？大数据程序员之家"},{"date":"2018-07-09 16:47:25","id":"7ce7782a7a6478f425d3b6eb56255d6c","title":"一年Android工作经验，阿里 百度 网易 美团 小米 快手面经科技百分百","content":"一年Android工作经验，阿里 百度 网易 美团 小米 快手面经科技百分百"},{"date":"2018-07-09 16:47:52","id":"b94cb799e277f5b42504882b75f54b50","title":"用 Bitcron 搭博客：你只管写作，它负责呈现少数派","content":"用 Bitcron 搭博客：你只管写作，它负责呈现少数派"},{"date":"2018-07-06 11:41:22","id":"6f6eb237de86a9c01e25060f084ad398","title":"谁说上班不能创业了，我就是那个边上班边创业的人火凤凰云创空间","content":"谁说上班不能创业了，我就是那个边上班边创业的人火凤凰云创空间"},{"date":"2018-07-06 11:16:55","id":"68ace6c90ca381f5bf9dae6fe2adf17b","title":"大数据怎样才能踏入进去？年薪60万大数据架构师教你如何入门！千年之狐大数据","content":"大数据怎样才能踏入进去？年薪60万大数据架构师教你如何入门！千年之狐大数据"},{"date":"2018-07-06 11:53:00","id":"a6aeda90bd07b1d9dd3321e9851613bf","title":"Requests爬取拉钩招聘信息Python笔录","content":"Requests爬取拉钩招聘信息Python笔录"},{"date":"2018-07-09 16:24:09","id":"bf148342fc9541f8358dfb552ff48308","title":"Android App增量，热修复，插件技术，让你的App维护起来更方便互联网生活那点事儿","content":"Android App增量，热修复，插件技术，让你的App维护起来更方便互联网生活那点事儿"}],"totalPage":79}}